[{"title":"Bohemian Rhapsody","artists":"Queen","startDate":"2 January 1992","endDate":"23 January 1992","posted":false},{"title":"Twilight Zone","artists":"2 Unlimited","startDate":"23 January 1992","endDate":"30 January 1992","posted":false},{"title":"Goodnight Girl","artists":"Wet Wet Wet","startDate":"30 January 1992","endDate":"27 February 1992","posted":false},{"title":"Stay","artists":"Shakespears Sister","startDate":"27 February 1992","endDate":"5 March 1992","posted":false},{"title":"One","artists":"U2","startDate":"5 March 1992","endDate":"12 March 1992","posted":false},{"title":"Stay","artists":"Shakespears Sister","startDate":"12 March 1992","endDate":"19 March 1992","posted":false},{"title":"Tears In Heaven","artists":"Eric Clapton","startDate":"19 March 1992","endDate":"26 March 1992","posted":false},{"title":"Stay","artists":"Shakespears Sister","startDate":"26 March 1992","endDate":"2 April 1992","posted":false},{"title":"Tears In Heaven","artists":"Eric Clapton","startDate":"2 April 1992","endDate":"9 April 1992","posted":false},{"title":"Stay","artists":"Shakespears Sister","startDate":"9 April 1992","endDate":"30 April 1992","posted":false},{"title":"Deeply Dippy","artists":"Right Said Fred","startDate":"30 April 1992","endDate":"28 May 1992","posted":false},{"title":"Why Me?","artists":"Linda Martin","startDate":"28 May 1992","endDate":"4 June 1992","posted":false},{"title":"Knockin on Heavens Door","artists":"Guns N' Roses","startDate":"4 June 1992","endDate":"11 June 1992","posted":false},{"title":"Jump","artists":"Kris Kross","startDate":"11 June 1992","endDate":"18 June 1992","posted":false},{"title":"Abba-esque","artists":"Erasure","startDate":"18 June 1992","endDate":"23 July 1992","posted":false},{"title":"Aint No Doubt","artists":"Jimmy Nail","startDate":"23 July 1992","endDate":"13 August 1992","posted":false},{"title":"Rhythm Is a Dancer","artists":"Snap!","startDate":"13 August 1992","endDate":"8 October 1992","posted":false},{"title":"Ebeneezer Goode","artists":"Shamen","startDate":"8 October 1992","endDate":"15 October 1992","posted":false},{"title":"Sleeping Satellite","artists":"Tasmin Archer","startDate":"15 October 1992","endDate":"12 November 1992","posted":false},{"title":"End of the Road","artists":"Boyz II Men","startDate":"12 November 1992","endDate":"3 December 1992","posted":false}]